README.md
setup.py
cfy_lint/__init__.py
cfy_lint/__version__.py
cfy_lint/cli.py
cfy_lint/helptexts.py
cfy_lint/logger.py
cfy_lint/main.py
cfy_lint.egg-info/PKG-INFO
cfy_lint.egg-info/SOURCES.txt
cfy_lint.egg-info/dependency_links.txt
cfy_lint.egg-info/entry_points.txt
cfy_lint.egg-info/requires.txt
cfy_lint.egg-info/top_level.txt
cfy_lint/commands/__init__.py
cfy_lint/commands/lint.py
cfy_lint/yamllint_ext/__init__.py
cfy_lint/yamllint_ext/constants.py
cfy_lint/yamllint_ext/generators.py
cfy_lint/yamllint_ext/overrides.py
cfy_lint/yamllint_ext/utils.py
cfy_lint/yamllint_ext/autofix/__init__.py
cfy_lint/yamllint_ext/autofix/add_label.py
cfy_lint/yamllint_ext/autofix/brackets.py
cfy_lint/yamllint_ext/autofix/colons.py
cfy_lint/yamllint_ext/autofix/commas.py
cfy_lint/yamllint_ext/autofix/deprecated_node_types.py
cfy_lint/yamllint_ext/autofix/deprecated_relationships.py
cfy_lint/yamllint_ext/autofix/empty_lines.py
cfy_lint/yamllint_ext/autofix/trailing_spaces.py
cfy_lint/yamllint_ext/autofix/truthy.py
cfy_lint/yamllint_ext/autofix/utils.py
cfy_lint/yamllint_ext/autofix/indentation/__init__.py
cfy_lint/yamllint_ext/autofix/indentation/constants.py
cfy_lint/yamllint_ext/autofix/indentation/utils.py
cfy_lint/yamllint_ext/cloudify/__init__.py
cfy_lint/yamllint_ext/cloudify/models.py
cfy_lint/yamllint_ext/config/__init__.py
cfy_lint/yamllint_ext/config/constants.py
cfy_lint/yamllint_ext/rules/__init__.py
cfy_lint/yamllint_ext/rules/blueprint_labels.py
cfy_lint/yamllint_ext/rules/capabilities.py
cfy_lint/yamllint_ext/rules/constants.py
cfy_lint/yamllint_ext/rules/dsl_definitions.py
cfy_lint/yamllint_ext/rules/dsl_version.py
cfy_lint/yamllint_ext/rules/imports.py
cfy_lint/yamllint_ext/rules/inputs.py
cfy_lint/yamllint_ext/rules/node_templates.py
cfy_lint/yamllint_ext/rules/node_types.py
cfy_lint/yamllint_ext/rules/relationships.py
cfy_lint/yamllint_ext/tests/__init__.py
cfy_lint/yamllint_ext/tests/test_autofix.py
cfy_lint/yamllint_ext/tests/test_generators.py
cfy_lint/yamllint_ext/tests/test_overrides.py
cfy_lint/yamllint_ext/tests/test_rules.py
cfy_lint/yamllint_ext/tests/test_utils.py