Metadata-Version: 2.1
Name: cfy-lint
Version: 0.0.37
Summary: Linter for Cloudify Blueprints
License: LICENSE
